MANIFEST.in
VERSION.txt
requirements.txt
setup.py
thecallrapi/__init__.py
thecallrapi/thecallr.py
thecallrapi.egg-info/PKG-INFO
thecallrapi.egg-info/SOURCES.txt
thecallrapi.egg-info/dependency_links.txt
thecallrapi.egg-info/requires.txt
thecallrapi.egg-info/top_level.txt