Metadata-Version: 1.1
Name: thecallrapi
Version: 1.0.4
Summary: Python module to manage TheCallr API
Home-page: UNKNOWN
Author: Optiflows R&D
Author-email: rand@surycat.com
License: UNKNOWN
Platform: UNKNOWN
Classifier: Development Status :: 5 - Production/Stable
Classifier: Intended Audience :: Developers
Classifier: Natural Language :: English
Classifier: Programming Language :: Python :: 3.4
Classifier: Programming Language :: Python :: 3.5
Classifier: Programming Language :: Python :: 3 :: Only
